<?xml version="1.0" encoding="UTF-8" standalone="no"?>
<quiz created="2017-10-31" edited="2017-11-04">
    <title>Zúg Március 2017</title>
    <question>
        <text>Ki terjesztett felirati javaslatot az országgyűlés elé, amelyben az érdekegyesítést és a belső reformokat jelölte meg célként?</text>
        <answer correct="true">
            <text>Kossuth Lajos</text>
        </answer>
        <answer correct="false">
            <text>Gróf Széchenyi István</text>
        </answer>
    </question>
    <question>
        <text>Milyen szervezet vitájának hatására nyerte el a március 15-ei változatát a 12 pont?</text>
        <answer correct="true">
            <text>Az Ellenzéki Kör</text>
        </answer>
        <answer correct="false">
            <text>Az Új Magyar nemzedék</text>
        </answer>
    </question>
    <question>
        <text>Melyik forradalom tört ki március 13-án?</text>
        <answer correct="true">
            <text>A bécsi forradalom</text>
        </answer>
        <answer correct="false">
            <text>A cseh forradalom, Prágában</text>
        </answer>
    </question>
    <question>
        <text>Melyik téren hallgatták először több ezren a Nemzeti Dalt és a kiáltványt?</text>
        <answer correct="true">
            <text>Az Egyetem téren</text>
        </answer>
        <answer correct="false">
            <text>A Kossuth téren</text>
        </answer>
    </question>
    <question>
        <text>Melyik híres nyilatkozat fogalmazza meg az emberi szabadság fogalmát?</text>
        <answer correct="true">
            <text>Az Emberi és Polgári Jogok Nyilatkozata</text>
        </answer>
        <answer correct="false">
            <text>Az Egyesült Államok függetlenségi nyilatkozata</text>
        </answer>
    </question>
    <question>
        <text>Kik figyelték a korabeli Magyarországon a nyomdák és a nyomtatott sajtók működését?</text>
        <answer correct="true">
            <text>A cenzurok</text>
        </answer>
        <answer correct="false">
            <text>A cenzusok</text>
        </answer>
        <answer correct="false">
            <text>A csendőrők</text>
        </answer>
        <answer correct="false">
            <text>A pandúrok</text>
        </answer>
    </question>
    <question>
        <text>Melyik esemény tette újra szabaddá a magyar sajtót?</text>
        <answer correct="true">
            <text>Az 1867-es kiegyezés</text>
        </answer>
        <answer correct="false">
            <text>A trianoni békeszerződés</text>
        </answer>
    </question>
    <question>
        <text>Az első felelős minisztérium előtt az irányítást ellátta.</text>
        <answer correct="true">
            <text>Az Udvari Kancellária</text>
        </answer>
        <answer correct="false">
            <text>A magyar kormány</text>
        </answer>
    </question>
    <question>
        <text>A forradalom idején a magyar kormány parlamenti üléseinek helyszíne.</text>
        <answer correct="true">
            <text>Pozsony</text>
        </answer>
        <answer correct="false">
            <text>Győr</text>
        </answer>
    </question>
    <question>
        <text>A kor kormányát az uralkodó hívhatta össze, ő főleg akkor tette ezt, ha..</text>
        <answer correct="true">
            <text>adót akart kiróni.</text>
        </answer>
        <answer correct="false">
            <text>törvényt akart elfogadtatni.</text>
        </answer>
    </question>
    <question>
        <text>A forradalom után a parlament újra ____ hívására gyűlt össze ____-ban.</text>
        <answer correct="true">
            <text>Ferenc József, 1861</text>
        </answer>
        <answer correct="false">
            <text>Deák Ferenc, 1867</text>
        </answer>
    </question>
    <question>
        <text>A nemesi előjogok helyett a ____ jogrendszert akarták kialakítani.</text>
        <answer correct="true">
            <text>polgári</text>
        </answer>
        <answer correct="false">
            <text>jobbágyi</text>
        </answer>
    </question>
    <question>
        <text>A Habsburgok hagyományosan a(z) ____ szövetségesei voltak.</text>
        <answer correct="true">
            <text>Vatikán</text>
        </answer>
        <answer correct="false">
            <text>Angol királyság</text>
        </answer>
    </question>
    <question>
        <text>A Batthány-kormány a nemzeti őrsereget ez okból fogadta el.</text>
        <answer correct="true">
            <text>A személyes és vagyonbiztonság, a közcsend és belbéke biztosítása érdekében</text>
        </answer>
        <answer correct="false">
            <text>A nemzet egysége, a haza védelme és a parlament hatalmának biztosítása érdekében</text>
        </answer>
    </question>
    <question>
        <text>A Mária Terézia által elrendelt úrbéri viszonyok fizetőeszközei a..</text>
        <answer correct="true">
            <text>munkavégzés, pénz, ajándék.</text>
        </answer>
        <answer correct="false">
            <text>föld, valuta, járulékok.</text>
        </answer>
    </question>
    <question>
        <text>A feudális bíráskodás rendszere alapján a különböző ítéleteket a ____ hozták meg.</text>
        <answer correct="false">
            <text>szakképzett jogászok</text>
        </answer>
        <answer correct="true">
            <text>földesurak</text>
        </answer>
    </question>
    <question>
        <text>A Magyar Kereskedelmi Bank forradalom utáni működése ekkor folytatódik.</text>
        <answer correct="false">
            <text>1908-ban.</text>
        </answer>
        <answer correct="true">
            <text>1924-ben.</text>
        </answer>
    </question>
    <question>
        <text>A kor legismertebb politikai foglya, Táncsics Mihály, ezen kihágás miatt volt letartóztatva.</text>
        <answer correct="false">
            <text>Sikkasztás</text>
        </answer>
        <answer correct="true">
            <text>Sajtóvétség</text>
        </answer>
    </question>
    <question>
        <text>Az önálló Erdély megalakulása után ____ év telt el az unió létrejöttéig.</text>
        <answer correct="false">
            <text>322</text>
        </answer>
        <answer correct="true">
            <text>307</text>
        </answer>
    </question>
    <question>
        <text>A magyar szabadságharc a ____ mintáját követte.</text>
        <answer correct="false">
            <text>az Amerikai függetlenségi háború</text>
        </answer>
        <answer correct="true">
            <text>a Francia forradalom</text>
        </answer>
    </question>
    <question>
        <text>A francia forradalom alapeszméi.</text>
        <answer correct="false">
            <text>Szabadság, adómentesség, szeretet</text>
        </answer>
        <answer correct="true">
            <text>Szabadság, egyenlőség, testvériség</text>
        </answer>
    </question>
    <question>
        <text>A Habsburg birodalom keretein belül..</text>
        <answer correct="false">
            <text>az önálló hadsereg létszáma korlátozott volt.</text>
        </answer>
        <answer correct="true">
            <text>nem létezett önálló hadsereg.</text>
        </answer>
    </question>
    <question>
        <text>Milyennek kellene lennie a törvénykezésnek a polgári normák szerint?</text>
        <answer correct="false">
            <text>Kifizethetőnek és kedvezőnek</text>
        </answer>
        <answer correct="true">
            <text>Függetlennek és mindenki által elérhetőnek</text>
        </answer>
    </question>
    <question>
        <text>A nemeseket adófizetésre kötelezi, miután az áprilisi törvények jogerősen kimondják.</text>
        <answer correct="false">
            <text>A kötelező adó törvényét</text>
        </answer>
        <answer correct="true">
            <text>A közös teherviselést</text>
        </answer>
    </question>
</quiz>
